README.md
pyproject.toml
setup.py
m_profiling_mf.egg-info/PKG-INFO
m_profiling_mf.egg-info/SOURCES.txt
m_profiling_mf.egg-info/dependency_links.txt
m_profiling_mf.egg-info/namespace_packages.txt
m_profiling_mf.egg-info/requires.txt
m_profiling_mf.egg-info/top_level.txt
mobio/libs/__init__.py
mobio/libs/profiling_mf/__init__.py
mobio/libs/profiling_mf/common_helper.py
mobio/libs/profiling_mf/profiling_common.py
mobio/libs/profiling_mf/profiling_helper.py
mobio/libs/profiling_mf/profiling_schema.py
mobio/libs/profiling_mf/merge_fields/__init__.py
mobio/libs/profiling_mf/merge_fields/base_merge.py
mobio/libs/profiling_mf/merge_fields/merge_address.py
mobio/libs/profiling_mf/merge_fields/merge_age.py
mobio/libs/profiling_mf/merge_fields/merge_avatar.py
mobio/libs/profiling_mf/merge_fields/merge_bank_cards.py
mobio/libs/profiling_mf/merge_fields/merge_birth_date.py
mobio/libs/profiling_mf/merge_fields/merge_birth_month.py
mobio/libs/profiling_mf/merge_fields/merge_birth_year.py
mobio/libs/profiling_mf/merge_fields/merge_birthday.py
mobio/libs/profiling_mf/merge_fields/merge_budget_high_threshold.py
mobio/libs/profiling_mf/merge_fields/merge_budget_low_threshold.py
mobio/libs/profiling_mf/merge_fields/merge_card_code.py
mobio/libs/profiling_mf/merge_fields/merge_card_id.py
mobio/libs/profiling_mf/merge_fields/merge_card_status.py
mobio/libs/profiling_mf/merge_fields/merge_cards.py
mobio/libs/profiling_mf/merge_fields/merge_childs.py
mobio/libs/profiling_mf/merge_fields/merge_cif.py
mobio/libs/profiling_mf/merge_fields/merge_clv.py
mobio/libs/profiling_mf/merge_fields/merge_company.py
mobio/libs/profiling_mf/merge_fields/merge_created_account_type.py
mobio/libs/profiling_mf/merge_fields/merge_created_time.py
mobio/libs/profiling_mf/merge_fields/merge_customer_created_time.py
mobio/libs/profiling_mf/merge_fields/merge_customer_id.py
mobio/libs/profiling_mf/merge_fields/merge_degree.py
mobio/libs/profiling_mf/merge_fields/merge_device_types.py
mobio/libs/profiling_mf/merge_fields/merge_devices.py
mobio/libs/profiling_mf/merge_fields/merge_district_code.py
mobio/libs/profiling_mf/merge_fields/merge_driver_license.py
mobio/libs/profiling_mf/merge_fields/merge_dynamic.py
